Metadata-Version: 2.1
Name: nlglib
Version: 0.2.1
Summary: Natural Language Generation library for Python
Home-page: https://github.com/roman-kutlak/nlglib
Author: Roman Kutlak
Author-email: kutlak.roman@gmail.com
License: MIT
Keywords: natural language generation,NLG,text generation,nlglib,library
Platform: UNKNOWN
Classifier: Development Status :: 4 - Beta
Classifier: Intended Audience :: Developers
Classifier: Intended Audience :: Science/Research
Classifier: Natural Language :: English
Classifier: License :: OSI Approved :: MIT License
Classifier: Operating System :: OS Independent
Classifier: Programming Language :: Python
Classifier: Programming Language :: Python :: 3
Classifier: Topic :: Scientific/Engineering :: Artificial Intelligence
Classifier: Topic :: Software Development :: Libraries
Classifier: Topic :: Text Processing :: Linguistic
Provides-Extra: dev
Requires-Dist: nltk
Provides-Extra: dev
Requires-Dist: coverage; extra == 'dev'
Requires-Dist: nose; extra == 'dev'
Requires-Dist: pycodestyle; extra == 'dev'
Requires-Dist: rednose; extra == 'dev'
